{
    "key": "group_5b0304243e565",
    "title": "Homepage - Statistics",
    "fields": [
        {
            "key": "field_5b0304325809d",
            "label": "Statistics",
            "name": "statistics",
            "type": "repeater",
            "instructions": "For best results, add 4 statistics.",
            "required": 0,
            "conditional_logic": 0,
            "wrapper": {
                "width": "",
                "class": "",
                "id": ""
            },
            "collapsed": "",
            "min": 0,
            "max": 4,
            "layout": "block",
            "button_label": "Add New Statistic",
            "sub_fields": [
                {
                    "key": "field_5b0304545809e",
                    "label": "Statistic Number",
                    "name": "stat_value",
                    "type": "text",
                    "instructions": "",
                    "required": 0,
                    "conditional_logic": 0,
                    "wrapper": {
                        "width": "20",
                        "class": "",
                        "id": ""
                    },
                    "default_value": "",
                    "placeholder": 92,
                    "prepend": "",
                    "append": "",
                    "maxlength": ""
                },
                {
                    "key": "field_5b03046c5809f",
                    "label": "Statistic Description",
                    "name": "stat_description",
                    "type": "text",
                    "instructions": "",
                    "required": 0,
                    "conditional_logic": 0,
                    "wrapper": {
                        "width": "20",
                        "class": "",
                        "id": ""
                    },
                    "default_value": "",
                    "placeholder": "years",
                    "prepend": "",
                    "append": "",
                    "maxlength": ""
                },
                {
                    "key": "field_5b03047f580a0",
                    "label": "Link Description",
                    "name": "hover_description",
                    "type": "text",
                    "instructions": "",
                    "required": 0,
                    "conditional_logic": 0,
                    "wrapper": {
                        "width": "20",
                        "class": "",
                        "id": ""
                    },
                    "default_value": "",
                    "placeholder": "View Films",
                    "prepend": "",
                    "append": "",
                    "maxlength": ""
                },
                {
                    "key": "field_5b03048b580a1",
                    "label": "Page Link",
                    "name": "link",
                    "type": "link",
                    "instructions": "",
                    "required": 0,
                    "conditional_logic": 0,
                    "wrapper": {
                        "width": "40",
                        "class": "",
                        "id": ""
                    },
                    "return_format": "array"
                }
            ]
        }
    ],
    "location": [
        [
            {
                "param": "page_template",
                "operator": "==",
                "value": "template-homepage.php"
            }
        ]
    ],
    "menu_order": 0,
    "position": "normal",
    "style": "seamless",
    "label_placement": "top",
    "instruction_placement": "label",
    "hide_on_screen": "",
    "active": 1,
    "description": "",
    "modified": 1527714006
}